{
  "rp2040_pio_led_strip.light": {
    "schemas": {
      "CONFIG_SCHEMA": {
        "schema": {
          "config_vars": {
            "bit0_high": {
              "key": "Optional"
            },
            "bit0_low": {
              "key": "Optional"
            },
            "bit1_high": {
              "key": "Optional"
            },
            "bit1_low": {
              "key": "Optional"
            },
            "chipset": {
              "key": "Optional",
              "type": "enum",
              "values": {
                "CUSTOM": null,
                "SK6812": null,
                "SM16703": null,
                "WS2812": null,
                "WS2812B": null
              }
            },
            "is_rgbw": {
              "default": "False",
              "key": "Optional",
              "type": "boolean"
            },
            "num_leds": {
              "data_type": "positive_not_null_int",
              "key": "Required",
              "type": "integer"
            },
            "output_id": {
              "id_type": {
                "class": "rp2040_pio_led_strip::RP2040PIOLEDStripLightOutput",
                "parents": [
                  "Component",
                  "light::AddressableLight",
                  "light::LightOutput"
                ]
              },
              "key": "GeneratedID"
            },
            "pin": {
              "internal": true,
              "key": "Required",
              "modes": [
                "output"
              ],
              "type": "pin"
            },
            "pio": {
              "key": "Required",
              "type": "enum",
              "values": {
                "0": null,
                "1": null
              }
            },
            "rgb_order": {
              "key": "Required",
              "type": "enum",
              "values": {
                "BGR": null,
                "BRG": null,
                "GBR": null,
                "GRB": null,
                "RBG": null,
                "RGB": null
              }
            }
          },
          "extends": [
            "light.ADDRESSABLE_LIGHT_SCHEMA"
          ]
        },
        "type": "schema"
      }
    }
  }
}